startstop/__about__.py
startstop/__init__.py
startstop-1.0.8.dist-info/METADATA
startstop-1.0.8.dist-info/WHEEL
startstop-1.0.8.dist-info/licenses/LICENSE.txt
startstop-1.0.8.dist-info/RECORD
