Metadata-Version: 2.1
Name: startstop
Version: 1.0.8
Summary: Start and stop a python profiler
Project-URL: homepage, https://github.com/1081/startstop
License-Expression: MIT
License-File: LICENSE.txt
Keywords: profiler,simple
Requires-Python: >=3.7
Requires-Dist: pyinstrument
